pydicom_seg/__init__.py
pydicom_seg/dicom_utils.py
pydicom_seg/externals/dcmqi/LICENSE.txt
pydicom_seg/externals/dcmqi/doc/schemas/common-schema.json
pydicom_seg/externals/dcmqi/doc/schemas/seg-schema.json
pydicom_seg/io.py
pydicom_seg/reader.py
pydicom_seg/reader_utils.py
pydicom_seg/segmentation_dataset.py
pydicom_seg/template.py
pydicom_seg/typing.py
pydicom_seg/writer.py
pydicom_seg/writer_utils.py
pydicom_seg/writer_v2.py
pydicom_seg-0.4.1.dist-info/LICENSE
pydicom_seg-0.4.1.dist-info/WHEEL
pydicom_seg-0.4.1.dist-info/METADATA
pydicom_seg-0.4.1.dist-info/RECORD
