Metadata-Version: 2.1
Name: pydicom-seg
Version: 0.4.1
Summary: Python package for DICOM-SEG medical segmentation file reading and writing
Home-page: https://github.com/razorx89/pydicom-seg
License: MIT
Author: Sven Koitka
Author-email: sven.koitka@uk-essen.de
Requires-Python: >=3.7,<4.0
Classifier: License :: OSI Approved :: MIT License
Classifier: Programming Language :: Python :: 3
Classifier: Programming Language :: Python :: 3.10
Classifier: Programming Language :: Python :: 3.7
Classifier: Programming Language :: Python :: 3.8
Classifier: Programming Language :: Python :: 3.9
Requires-Dist: SimpleITK (>1.2.4)
Requires-Dist: jsonschema (>=3.2.0,<4.0.0)
Requires-Dist: numpy (>=1.18.0,<2.0.0)
Requires-Dist: pydicom (>=1.4.2)
